compliance_suite/__init__.py
compliance_suite/constants.py
compliance_suite/generate_json.py
compliance_suite/helper.py
compliance_suite/report.py
compliance_suite/report_runner.py
compliance_suite/report_server.py
compliance_suite/validate_drs_object_response.py
compliance_suite/validate_response.py
compliance_suite/config/config_basic.json
compliance_suite/config/config_bearer.json
compliance_suite/config/config_none.json
compliance_suite/config/config_passport.json
compliance_suite/config/input_drs_objects.json
compliance_suite/interactions/drs_object.json
compliance_suite/interactions/service_info.json
compliance_suite/schemas/access_method.json
compliance_suite/schemas/access_url.json
compliance_suite/schemas/checksum.json
compliance_suite/schemas/contents_object.json
compliance_suite/schemas/drs_object.json
compliance_suite/schemas/error.json
compliance_suite/schemas/service_info.json
compliance_suite/schemas/service_type.json
compliance_suite/schemas/v1.2.0/access_method.json
compliance_suite/schemas/v1.2.0/access_url.json
compliance_suite/schemas/v1.2.0/checksum.json
compliance_suite/schemas/v1.2.0/contents_object.json
compliance_suite/schemas/v1.2.0/drs_bundle.json
compliance_suite/schemas/v1.2.0/drs_object.json
compliance_suite/schemas/v1.2.0/error.json
drs_compliance_test-1.0.2.dist-info/LICENSE
drs_compliance_test-1.0.2.dist-info/METADATA
drs_compliance_test-1.0.2.dist-info/WHEEL
drs_compliance_test-1.0.2.dist-info/entry_points.txt
drs_compliance_test-1.0.2.dist-info/top_level.txt
drs_compliance_test-1.0.2.dist-info/RECORD
